{
  "0": {
    "id": 6,
    "name": "Abbott-Schmitt",
    "image": " https://raw.githubusercontent.com/SBobi/fud-photos/main/Restaurant/8.jpg",
    "lat": 4.611266353849539,
    "lon": -73.10041917702685
  },
  "1": {
    "id": 7,
    "name": "Reynolds Group",
    "image": " https://raw.githubusercontent.com/SBobi/fud-photos/main/Restaurant/8.jpg",
    "lat": 4.816365201213659,
    "lon": -73.34142592544812
  },
  "2": {
    "id": 8,
    "name": "Kessler-Schaefer",
    "image": " https://raw.githubusercontent.com/SBobi/fud-photos/main/Restaurant/9.jpg",
    "lat": 5.317398530964697,
    "lon": -73.84689052375538
  },
  "3": {
    "id": 9,
    "name": "Price",
    "image": " https://raw.githubusercontent.com/SBobi/fud-photos/main/Restaurant/8.jpg",
    "lat": 4.74086510769831,
    "lon": -73.26517887580926
  },
  "4": {
    "id": 10,
    "name": "Reichert",
    "image": " https://raw.githubusercontent.com/SBobi/fud-photos/main/Restaurant/9.jpg",
    "lat": 4.646106804981657,
    "lon": -73.6142096338407
  },
  "5": {
    "id": 11,
    "name": "Boyer-Baumbach",
    "image": " https://raw.githubusercontent.com/SBobi/fud-photos/main/Restaurant/4.jpg",
    "lat": 4.754534416283136,
    "lon": -73.58807279565124
  },
  "6": {
    "id": 12,
    "name": "White LLC",
    "image": " https://raw.githubusercontent.com/SBobi/fud-photos/main/Restaurant/9.jpg",
    "lat": 4.6757302329274,
    "lon": -73.17175753246028
  },
  "7": {
    "id": 13,
    "name": "Schumm Inc",
    "image": " https://raw.githubusercontent.com/SBobi/fud-photos/main/Restaurant/2.jpg",
    "lat": 4.857484802696353,
    "lon": -73.47542733517744
  },
  "8": {
    "id": 14,
    "name": "Koepp-Wintheiser",
    "image": " https://raw.githubusercontent.com/SBobi/fud-photos/main/Restaurant/8.jpg",
    "lat": 4.74412252693535,
    "lon": -73.3410596509555
  },
  "9": {
    "id": 15,
    "name": "Ullrich Inc",
    "image": " https://raw.githubusercontent.com/SBobi/fud-photos/main/Restaurant/4.jpg",
    "lat": 4.722384697973218,
    "lon": -73.74517396471153
  }
}
